geoffrey_jshint-0.0.1.dist-info/DESCRIPTION.rst
geoffrey_jshint-0.0.1.dist-info/RECORD
geoffrey_jshint-0.0.1.dist-info/WHEEL
geoffrey_jshint-0.0.1.dist-info/top_level.txt
geoffrey_jshint-0.0.1.dist-info/metadata.json
geoffrey_jshint-0.0.1.dist-info/METADATA
geoffreyplugins/__init__.py
geoffreyplugins/jshint.py
geoffreyplugins/jshint/main.js
geoffreyplugins/jshint/assets/.gitkeep
