Metadata-Version: 2.0
Name: geoffrey-jshint
Version: 0.0.1
Summary: JSHint is a community-driven tool to detect errors and potential problems in JavaScript code
Home-page: https://github.com/GeoffreyCI/geoffrey-jshint
Author: Miguel Reguero Bejar
Author-email: mreguerob0@gmail.com
License: UNKNOWN
Platform: UNKNOWN
